CLAWSTag/Tagger.py
CLAWSTag/__init__.py
CLAWSTag-0.0.2.1.dist-info/LICENSE
CLAWSTag-0.0.2.1.dist-info/METADATA
CLAWSTag-0.0.2.1.dist-info/WHEEL
CLAWSTag-0.0.2.1.dist-info/top_level.txt
CLAWSTag-0.0.2.1.dist-info/RECORD
