Metadata-Version: 2.1
Name: CLAWSTag
Version: 0.0.2.1
Summary: an English POS tagging tool based on the free CLAWS web tagger API by Lancaster University
Home-page: UNKNOWN
Author: VictorWWQ
Author-email: VictorWWQ@163.com
License: UNKNOWN
Platform: UNKNOWN
Classifier: Programming Language :: Python :: 3
Classifier: License :: OSI Approved :: MIT License
Classifier: Operating System :: OS Independent
Requires-Python: >=3.6
Requires-Dist: requests
Requires-Dist: beautifulsoup4
Requires-Dist: Faker
